datamarket/__init__.py
datamarket/exceptions/__init__.py
datamarket/exceptions/main.py
datamarket/interfaces/__init__.py
datamarket/interfaces/alchemy.py
datamarket/interfaces/aws.py
datamarket/interfaces/azure.py
datamarket/interfaces/drive.py
datamarket/interfaces/ftp.py
datamarket/interfaces/llm.py
datamarket/interfaces/nominatim.py
datamarket/interfaces/peerdb.py
datamarket/interfaces/proxy.py
datamarket/interfaces/tinybird.py
datamarket/params/__init__.py
datamarket/params/nominatim.py
datamarket/utils/__init__.py
datamarket/utils/airflow.py
datamarket/utils/alchemy.py
datamarket/utils/logs.py
datamarket/utils/main.py
datamarket/utils/nominatim.py
datamarket/utils/playwright/__init__.py
datamarket/utils/playwright/async_api.py
datamarket/utils/playwright/sync_api.py
datamarket/utils/requests.py
datamarket/utils/selenium.py
datamarket/utils/soda.py
datamarket/utils/strings/__init__.py
datamarket/utils/strings/normalization.py
datamarket/utils/strings/obfuscation.py
datamarket/utils/strings/standardization.py
datamarket/utils/typer.py
datamarket/utils/types.py
datamarket-0.10.2.dist-info/METADATA
datamarket-0.10.2.dist-info/WHEEL
datamarket-0.10.2.dist-info/licenses/LICENSE
datamarket-0.10.2.dist-info/RECORD
